{
  "extends": "tslint:recommended",
  "rules": {
    "align": false,
    "member-access": false,
    "member-ordering": false,
    "object-literal-shorthand": false,
    "max-classes-per-file": false,
    "max-line-length": false,
    "no-empty": false,
    "object-literal-sort-keys": false,
    "no-empty-interface": false,
    "triple-equals": false,
    "no-console": false,
    "interface-name": false,

    "no-unnecessary-type-assertion": true,
    "no-for-in-array": true,
    "no-unbound-method": true,
    "no-boolean-literal-compare": true,
    "unnecessary-bind": true,
    "no-string-literal": true,
    "no-unsafe-any": true,
    "no-any": true,
    "strict-string-expressions": true,

    "strict-boolean-expressions": false,
    "restrict-plus-operands": false,
    "strict-type-predicates": false
  },
  "defaultSeverity": "error"
}
